traixroute-2.3.dist-info/DESCRIPTION.rst
traixroute-2.3.dist-info/RECORD
traixroute-2.3.dist-info/entry_points.txt
traixroute-2.3.dist-info/top_level.txt
traixroute-2.3.dist-info/WHEEL
traixroute-2.3.dist-info/METADATA
traixroute-2.3.dist-info/metadata.json
traixroute/application.py
traixroute/__init__.py
traixroute/configuration/additional_info.txt
traixroute/configuration/rules.txt
traixroute/configuration/delimeters.txt
traixroute/configuration/config
traixroute/configuration/expressions.txt
traixroute/handler/handle_remote.py
traixroute/handler/handle_complementary.py
traixroute/handler/handle_ripe.py
traixroute/handler/handle_json.py
traixroute/handler/database_extract.py
traixroute/handler/handle_pdb.py
traixroute/handler/handle_pch.py
traixroute/handler/dict_merger.py
traixroute/handler/__init__.py
traixroute/controller/traixroute_parser.py
traixroute/controller/traixroute_output.py
traixroute/controller/string_handler.py
traixroute/controller/__init__.py
traixroute/pathinfo/path_info_extraction.py
traixroute/pathinfo/__init__.py
traixroute/tracetools/__init__.py
traixroute/tracetools/trace_tool.py
traixroute/database/RemotePeering/remote_interfaces.Any2 Los Angeles.20160801-geolocated.json
traixroute/database/RemotePeering/remote_interfaces.AMS-IX.20160801-geo-rtt-CORRECTED-offset.json
traixroute/database/RemotePeering/remote_interfaces.DE-CIX Frankfurt.20160801-geo-rtt-CORRECTED-offset.json
traixroute/database/RemotePeering/remote_interfaces.MSK-IX.20160801-geo-rtt-CORRECTED.json
traixroute/database/RemotePeering/remote_interfaces.LINX Juniper LAN.20160801-geolocated.json
traixroute/database/RemotePeering/remote_interfaces.France-IX.20160801-geolocated.json
traixroute/database/Default/PCH/ixp_membership.csv
traixroute/database/Default/PCH/ixp_subnets.csv
traixroute/database/Default/PCH/ixp_exchange.csv
traixroute/database/Default/RouteViews/routeviews
traixroute/database/Default/PDB/ixpfx.json
traixroute/database/Default/PDB/ix.json
traixroute/database/Default/PDB/ixlan.json
traixroute/database/Default/PDB/netixlan.json
traixroute/downloader/download_files.py
traixroute/downloader/install_scamper.py
traixroute/downloader/__init__.py
