Metadata-Version: 2.0
Name: traixroute
Version: 2.3
Summary: A tool that detects at which hop in a traceroute path an IXP fabric has been crossed.
Home-page: https://github.com/gnomikos/traIXroute
Author: Michalis Bamiedakis, Dimitris Mavrommatis and George Nomikos
Author-email: gnomikos@ics.forth.gr
License: GNU General Public License v3 (GPLv3)
Keywords: traIXroute Internet Exchange Points crossing traceroute ripe atlas
Platform: linux-x86_64
Classifier: Development Status :: 5 - Production/Stable
Classifier: License :: OSI Approved :: GNU General Public License v3 (GPLv3)
Classifier: Programming Language :: Python :: 3 :: Only
Classifier: Programming Language :: Python :: 3.4
Classifier: Programming Language :: Python :: 3.5
Classifier: Topic :: Internet
Classifier: Intended Audience :: Telecommunications Industry
Classifier: Environment :: Console
Requires-Dist: setuptools
Requires-Dist: cffi (==1.7.0)
Requires-Dist: cryptography (==2.1.4)
Requires-Dist: idna (==2.1)
Requires-Dist: pyasn1 (==0.1.9)
Requires-Dist: pycparser (==2.14)
Requires-Dist: pyOpenSSL (==17.4.0)
Requires-Dist: pysubnettree (==0.26)
Requires-Dist: python-dateutil (==2.5.3)
Requires-Dist: pytz (==2016.6.1)
Requires-Dist: requests (==2.18.4)
Requires-Dist: ripe.atlas.cousteau (==1.4)
Requires-Dist: ripe.atlas.sagan (==1.1.11)
Requires-Dist: six (==1.11.0)
Requires-Dist: socketIO-client (==0.7.0)
Requires-Dist: ujson (==1.35)
Requires-Dist: websocket-client (==0.37.0)
Requires-Dist: fuzzywuzzy[speedup] (==0.16.0)
Requires-Dist: netaddr (==0.7.19)
